my_assert-0.0.2.dist-info/DESCRIPTION.rst
my_assert-0.0.2.dist-info/METADATA
my_assert-0.0.2.dist-info/RECORD
my_assert-0.0.2.dist-info/WHEEL
my_assert-0.0.2.dist-info/metadata.json
my_assert-0.0.2.dist-info/top_level.txt
myassert/__init__.py
myassert/assertions.py
myassert/error_messages.py
