Metadata-Version: 2.0
Name: my-assert
Version: 0.0.2
Summary: Simple assertion library with verbose error messages
Home-page: https://github.com/thaffenden/myassert
Author: Tristan Haffenden
Author-email: tristanehaffenden@gmail.com
License: UNKNOWN
Platform: UNKNOWN
